{
	"animations": [
		{
			"loop": true,
			"offsets": [
				0,
				-2
			],
			"anim": "idle",
			"fps": 24,
			"name": "sly idle",
			"indices": []
		},
		{
			"loop": false,
			"offsets": [
				49,
				-5
			],
			"anim": "singDOWN",
			"fps": 24,
			"name": "down",
			"indices": []
		},
		{
			"loop": false,
			"offsets": [
				273,
				470
			],
			"anim": "singUP",
			"fps": 24,
			"name": "up",
			"indices": []
		},
		{
			"loop": false,
			"offsets": [
				288,
				446
			],
			"anim": "singRIGHT",
			"fps": 24,
			"name": "right",
			"indices": []
		},
		{
			"loop": false,
			"offsets": [
				120,
				9
			],
			"anim": "singLEFT",
			"fps": 24,
			"name": "left",
			"indices": []
		}
	],
	"no_antialiasing": false,
	"image": "characters/nightmaresly",
	"position": [
		0,
		0
	],
	"healthicon": "nightmaresly",
	"flip_x": false,
	"healthbar_colors": [
		95,
		0,
		0
	],
	"camera_position": [
		0,
		0
	],
	"sing_duration": 4,
	"scale": 1
}